ntdocutils/__init__.py
ntdocutils/cmdline.py
ntdocutils/exceptions.py
ntdocutils/writer.py
ntdocutils-1.0.1.dist-info/licenses/LICENSE
ntdocutils-1.0.1.dist-info/METADATA
ntdocutils-1.0.1.dist-info/WHEEL
ntdocutils-1.0.1.dist-info/entry_points.txt
ntdocutils-1.0.1.dist-info/top_level.txt
ntdocutils-1.0.1.dist-info/RECORD
