Metadata-Version: 2.4
Name: ntDocutils
Version: 1.0.1
Summary: ntDocutils is a theme manager for Docutils.
Home-page: https://ntrrg.dev/en/projects/ntdocutils
Author: Miguel Angel Rivera Notararigo
Author-email: ntrrgx@gmail.com
License: MIT
Keywords: docutils restructuredtext docutils-theme-manager docutils-themes documentation
Classifier: Development Status :: 5 - Production/Stable
Classifier: Environment :: Console
Classifier: Intended Audience :: End Users/Desktop
Classifier: Intended Audience :: Other Audience
Classifier: Intended Audience :: Developers
Classifier: Intended Audience :: Science/Research
Classifier: Intended Audience :: System Administrators
Classifier: Topic :: Documentation
Classifier: Topic :: Software Development :: Documentation
Classifier: Topic :: Text Processing
Classifier: Programming Language :: Python :: 3
License-File: LICENSE
Requires-Dist: docutils==0.22.3
Requires-Dist: Pygments==2.19.2
Dynamic: author
Dynamic: author-email
Dynamic: classifier
Dynamic: description
Dynamic: description-content-type
Dynamic: home-page
Dynamic: keywords
Dynamic: license
Dynamic: license-file
Dynamic: requires-dist
Dynamic: summary
